setup.cfg
setup.py
pygments_lexer_pseudocode/__init__.py
pygments_lexer_pseudocode.egg-info/PKG-INFO
pygments_lexer_pseudocode.egg-info/SOURCES.txt
pygments_lexer_pseudocode.egg-info/dependency_links.txt
pygments_lexer_pseudocode.egg-info/entry_points.txt
pygments_lexer_pseudocode.egg-info/requires.txt
pygments_lexer_pseudocode.egg-info/top_level.txt