Metadata-Version: 1.1
Name: pygments-lexer-pseudocode
Version: 2.0.1
Summary: Pygments Lexer for a french pseudocode
Home-page: https://github.com/svvac/pseudocode-pygments-lexer
Author: Simon Wachter
Author-email: simon@wachter.me
License: MIT
Platform: UNKNOWN
Classifier: Development Status :: 4 - Beta
Classifier: License :: OSI Approved :: MIT License
Classifier: Natural Language :: French
Classifier: Topic :: Text Processing
Classifier: Topic :: Utilities
